{"results":[{"gender":"male","name":{"title":"mr","first":"eli","last":"foster"},"location":{"street":"5069 ranchview dr","city":"busselton","state":"new south wales","postcode":1550,"coordinates":{"latitude":"-83.7806","longitude":"-27.9069"},"timezone":{"offset":"-4:00","description":"Atlantic Time (Canada), Caracas, La Paz"}},"email":"eli.foster@example.com","login":{"uuid":"4447b330-f3fe-4308-ae51-fe7ec067bbeb","username":"greencat979","password":"team","salt":"8p04mbHO","md5":"15844c0783d594ca22a3ee02b07c4944","sha1":"73d3fbfb5d6e2156fcd82726eedc769d306fe1d3","sha256":"aafaca1e64153dfe5a2863c5b43fbb00fdd5c92dde277cabc34d3ab65914a45f"},"dob":{"date":"1992-12-09T01:56:12Z","age":26},"registered":{"date":"2009-05-26T21:01:58Z","age":10},"phone":"08-0446-7977","cell":"0437-574-665","id":{"name":"TFN","value":"712042198"},"picture":{"large":"https://randomuser.me/api/portraits/men/88.jpg","medium":"https://randomuser.me/api/portraits/med/men/88.jpg","thumbnail":"https://randomuser.me/api/portraits/thumb/men/88.jpg"},"nat":"AU"},{"gender":"male","name":{"title":"mr","first":"christopher","last":"simpson"},"location":{"street":"8299 green lane","city":"drogheda","state":"galway","postcode":94745,"coordinates":{"latitude":"43.7035","longitude":"-55.2989"},"timezone":{"offset":"+2:00","description":"Kaliningrad, South Africa"}},"email":"christopher.simpson@example.com","login":{"uuid":"b8b69a9c-1416-442e-928a-72d8d354f78e","username":"yellowdog921","password":"hallowee","salt":"BH6Y1RZG","md5":"3d2f9252b80156f74c612631334caedb","sha1":"956c94dabf94c1de4b5626bb9d23a8d2a1736f9f","sha256":"cdbb0bdfe91a73b37f3c30d387de672f7803ae28548a5a97125d55d8d1903be7"},"dob":{"date":"1988-02-24T12:13:24Z","age":31},"registered":{"date":"2006-11-01T17:35:42Z","age":12},"phone":"021-684-9669","cell":"081-360-2441","id":{"name":"PPS","value":"9789087T"},"picture":{"large":"https://randomuser.me/api/portraits/men/77.jpg","medium":"https://randomuser.me/api/portraits/med/men/77.jpg","thumbnail":"https://randomuser.me/api/portraits/thumb/men/77.jpg"},"nat":"IE"},{"gender":"female","name":{"title":"ms","first":"maëlia","last":"rousseau"},"location":{"street":"6521 rue des chartreux","city":"caen","state":"côte-d'or","postcode":49813,"coordinates":{"latitude":"57.7383","longitude":"125.5073"},"timezone":{"offset":"+10:00","description":"Eastern Australia, Guam, Vladivostok"}},"email":"maëlia.rousseau@example.com","login":{"uuid":"bd86f2ed-4c49-4e7e-99e4-a04672ebde0d","username":"whitegorilla235","password":"supra","salt":"yF9ly5jn","md5":"3a2b88586217302f557f06a673c93dc4","sha1":"ac101994a7f475568266ee2faec27933da7b8c0b","sha256":"9dadb4954be213c9f582fe3a84f53314790049a9f95da05ad6e31005553169fe"},"dob":{"date":"1977-02-21T17:53:38Z","age":42},"registered":{"date":"2015-12-11T02:18:48Z","age":3},"phone":"05-76-50-47-54","cell":"06-56-90-30-88","id":{"name":"INSEE","value":"2NNaN71198184 12"},"picture":{"large":"https://randomuser.me/api/portraits/women/90.jpg","medium":"https://randomuser.me/api/portraits/med/women/90.jpg","thumbnail":"https://randomuser.me/api/portraits/thumb/women/90.jpg"},"nat":"FR"},{"gender":"male","name":{"title":"mr","first":"ivan","last":"rojas"},"location":{"street":"4553 calle de la democracia","city":"córdoba","state":"país vasco","postcode":54577,"coordinates":{"latitude":"46.2086","longitude":"2.2118"},"timezone":{"offset":"-3:00","description":"Brazil, Buenos Aires, Georgetown"}},"email":"ivan.rojas@example.com","login":{"uuid":"9becfab3-3768-4f26-a23d-e629deecb817","username":"smalldog243","password":"tigger1","salt":"2Idc5QbS","md5":"ea944dda021da40806b6fe5a2095dba3","sha1":"05d452138399c133bd4e638c099ad5890efa5052","sha256":"0ee1f2ce3ab3e7c6a304b357c7f0fda863e35eb8639c881223538e92dba9fdbf"},"dob":{"date":"1959-10-03T17:11:33Z","age":59},"registered":{"date":"2005-03-02T14:27:17Z","age":14},"phone":"967-678-769","cell":"612-019-407","id":{"name":"DNI","value":"27007965-K"},"picture":{"large":"https://randomuser.me/api/portraits/men/30.jpg","medium":"https://randomuser.me/api/portraits/med/men/30.jpg","thumbnail":"https://randomuser.me/api/portraits/thumb/men/30.jpg"},"nat":"ES"},{"gender":"female","name":{"title":"mademoiselle","first":"janine","last":"chevalier"},"location":{"street":"4422 rue saint-georges","city":"vallorbe","state":"schwyz","postcode":4072,"coordinates":{"latitude":"53.4683","longitude":"0.4059"},"timezone":{"offset":"+3:00","description":"Baghdad, Riyadh, Moscow, St. Petersburg"}},"email":"janine.chevalier@example.com","login":{"uuid":"68af151d-dc11-4ed2-9615-608c5783e7d8","username":"yellowgoose250","password":"killers","salt":"1AyXpauy","md5":"34f6a47320a00399f432f0a5249838bb","sha1":"14cabe51d1f06c6ddd267ddae689b58d24e9ba04","sha256":"b8f49ac290b0217d0cb445e2f39d3bfcabae3d2aa5c0332d7cc465626f374e82"},"dob":{"date":"1972-10-11T21:25:27Z","age":46},"registered":{"date":"2011-04-12T08:15:32Z","age":8},"phone":"(927)-549-6266","cell":"(668)-641-6086","id":{"name":"AVS","value":"756.3454.0484.48"},"picture":{"large":"https://randomuser.me/api/portraits/women/69.jpg","medium":"https://randomuser.me/api/portraits/med/women/69.jpg","thumbnail":"https://randomuser.me/api/portraits/thumb/women/69.jpg"},"nat":"CH"}],"info":{"seed":"14e16ccccd9dc8f4","results":5,"page":1,"version":"1.2"}}